[
  {
    "text": "-a-",
    "function": "Simple vowel bridge for flow"
  },
  {
    "text": "-e-",
    "function": "Simple vowel bridge for flow"
  },
  {
    "text": "-o-",
    "function": "Simple vowel bridge for flow"
  },
  {
    "text": "-an-",
    "function": "Spirit / Common smooth bridge",
    "meaning": "Spirit"
  },
  {
    "text": "-ani-",
    "function": "Implies \"spirit of\" or \"essence of\"",
    "meaning": "Spirit Of, Essence Of"
  },
  {
    "text": "-ea-",
    "function": "Adds a pause or weight to the name"
  },
  {
    "text": "-ella-",
    "function": "gentle, elegant",
    "meaning": "Gentle, Elegant"
  },
  {
    "text": "-en-",
    "function": "Breaks up harsh consonants to add softness, often means \"small\" or \"dear\"",
    "meaning": "Small, Dear"
  },
  {
    "text": "-i-",
    "function": "A soft connector bridge that breaks up the consonants"
  },
  {
    "text": "-il-",
    "function": "Common Moon Elf bridge; adds a \"silvery\" sound"
  },
  {
    "text": "-ira-",
    "function": "dreaming, soul-deep",
    "meaning": "Dreaming, Soul-Deep"
  },
  {
    "text": "-la-",
    "function": "grace, beauty",
    "meaning": "Grace, Beauty"
  },
  {
    "text": "-lë-",
    "function": "A melodic, quick bridge (from telë or la) often used for Moon/Star root to a status suffix"
  },
  {
    "text": "-na-",
    "function": "heart, spirit",
    "meaning": "Heart, Spirit"
  },
  {
    "text": "-or-",
    "function": "Adds a sturdy or strong tone"
  },
  {
    "text": "-ri-",
    "function": "light, movement",
    "meaning": "Light, Movement"
  },
  {
    "text": "-sae-",
    "function": "sky, ethereal",
    "meaning": "Sky, Ethereal"
  },
  {
    "text": "-sha-",
    "function": "moonlit, enchanted",
    "meaning": "Moonlit, Enchanted"
  },
  {
    "text": "-th-",
    "function": "Separates two vowels or a consonant and a vowel for an airy sound."
  },
  {
    "text": "-the-",
    "function": "kin, heritage",
    "meaning": "Kin, Heritage"
  },
  {
    "text": "-v-",
    "function": "Very rare; Used when the root already contains an 'r' or 'l' and another vowel is needed."
  },
  {
    "text": "-va-",
    "function": "strength, vitality",
    "meaning": "Strength, Vitality"
  },
  {
    "text": "-yr-",
    "function": "Used between two strong consonants to add a rich, ancient, or rare tone"
  }
]